MANIFEST.in
README.md
requirements.txt
setup.cfg
setup.py
site_pinger/__init__.py
site_pinger/__main__.py
site_pinger/utils.py
site_pinger.egg-info/PKG-INFO
site_pinger.egg-info/SOURCES.txt
site_pinger.egg-info/dependency_links.txt
site_pinger.egg-info/entry_points.txt
site_pinger.egg-info/requires.txt
site_pinger.egg-info/top_level.txt
site_pinger/core/__init__.py
site_pinger/core/conf.py
site_pinger/core/email_sender.py
site_pinger/core/fields.py
site_pinger/core/forms.py