Metadata-Version: 1.1
Name: site-pinger
Version: 0.4.0
Summary: python program for check work in site urls
Home-page: https://github.com/assigdev/site_pinger
Author: Arsen Khalilov
Author-email: assigdev@gmail.com
License: BSD
Download-URL: https://github.com/assigdev/site_pinger/tarball/0.4.0
Keywords: util,test site,ping
Platform: UNKNOWN
Classifier: Development Status :: 3 - Alpha
Classifier: Intended Audience :: Developers
Classifier: Programming Language :: Python :: 3
Classifier: Environment :: Console
Classifier: Environment :: Web Environment
Classifier: Operating System :: POSIX :: Linux
Classifier: Topic :: System :: Monitoring
Classifier: Topic :: Utilities
Classifier: Topic :: Internet :: WWW/HTTP
